setup.py
cmuclmtk/__init__.py
cmuclmtk.egg-info/PKG-INFO
cmuclmtk.egg-info/SOURCES.txt
cmuclmtk.egg-info/dependency_links.txt
cmuclmtk.egg-info/top_level.txt
cmuclmtk.egg-info/zip-safe