Metadata-Version: 1.0
Name: cmuclmtk
Version: 0.1.5
Summary: Wrapper library for accessing the language model tools for CMU Sphinx (CMUCLMTK).
Home-page: https://github.com/Holzhaus/python-cmuclmtk
Author: Jan Holthuis
Author-email: holthuis.jan@googlemail.com
License: BSD
Keywords: cmu sphinx cmuclmtk language modeling training vocabulary dictionary vocab dict
Platform: UNKNOWN
